nparraymapper/README.MD
nparraymapper/__init__.py
nparraymapper/requirements.txt
nparraymapper/thirdparty.json
nparraymapper-0.10.dist-info/LICENSE.rst
nparraymapper-0.10.dist-info/METADATA
nparraymapper-0.10.dist-info/WHEEL
nparraymapper-0.10.dist-info/top_level.txt
nparraymapper-0.10.dist-info/RECORD
