Metadata-Version: 2.1
Name: nparraymapper
Version: 0.10
Summary: Mapping values in NumPy arrays (any shape!) with high speed - Cython -
Home-page: https://github.com/hansalemaos/nparraymapper
Author: Johannes Fischer
Author-email: aulasparticularesdealemaosp@gmail.com
License: MIT
Keywords: rgb,Cython
Classifier: Development Status :: 4 - Beta
Classifier: Programming Language :: Python :: 3 :: Only
Classifier: Programming Language :: Python :: 3.10
Classifier: Topic :: Software Development :: Libraries :: Python Modules
Classifier: Topic :: Utilities
License-File: LICENSE.rst
Requires-Dist: Cython
Requires-Dist: numpy
